exotethys/_0database.pickle
exotethys/__init__.py
exotethys/_database.py
exotethys/boats.py
exotethys/manage_database.py
exotethys/sail.py
exotethys/trip.py
exotethys/Passbands/HST_STIS_G430L.pass
exotethys/Passbands/HST_STIS_G750L.pass
exotethys/Passbands/HST_WFC3_G102.pass
exotethys/Passbands/HST_WFC3_G141.pass
exotethys/Passbands/JWST_MIRI_LRS_Slitless.pass
exotethys/Passbands/JWST_NIRCAM_F322W2.pass
exotethys/Passbands/JWST_NIRISS_SOSS_order1.pass
exotethys/Passbands/JWST_NIRISS_SOSS_order2.pass
exotethys/Passbands/JWST_NIRSPEC_G395H.pass
exotethys/Passbands/JWST_NIRSPEC_PRISM.pass
exotethys/Passbands/Johnson_B.pass
exotethys/Passbands/Johnson_R.pass
exotethys/Passbands/Johnson_U.pass
exotethys/Passbands/Johnson_V.pass
exotethys/Passbands/Kepler.pass
exotethys/Passbands/Spitzer_IRAC1_subarray.pass
exotethys/Passbands/Spitzer_IRAC2_subarray.pass
exotethys/Passbands/Spitzer_IRAC3_subarray.pass
exotethys/Passbands/Spitzer_IRAC4_subarray.pass
exotethys/Passbands/TESS.pass
exotethys/Passbands/uniform_atlas_2000.pass
exotethys/Passbands/uniform_phoenix_2012_13.pass
exotethys/Passbands/uniform_phoenix_2018.pass
exotethys/Passbands/uniform_phoenix_drift_2012.pass
exotethys/Passbands/uniform_stagger_2015.pass
exotethys/Passbands/uniform_stagger_2018.pass
exotethys-2.0.15.data/data/README.adoc
exotethys-2.0.15.dist-info/LICENSE
exotethys-2.0.15.dist-info/METADATA
exotethys-2.0.15.dist-info/WHEEL
exotethys-2.0.15.dist-info/top_level.txt
exotethys-2.0.15.dist-info/RECORD
