Metadata-Version: 2.1
Name: exotethys
Version: 2.0.15
Home-page: https://github.com/ucl-exoplanets/ExoTETHyS
Author: Giuseppe Morello
Author-email: giuseppe.morello.11@ucl.ac.uk
License: GNU General Public License v3 (GPLv3)
Classifier: Development Status :: 4 - Beta
Classifier: Environment :: Console
Classifier: Intended Audience :: Science/Research
Classifier: Topic :: Scientific/Engineering :: Astronomy
Classifier: Operating System :: MacOS :: MacOS X
Classifier: Programming Language :: Python :: 3.7
License-File: LICENSE
Requires-Dist: scipy>=1.2.2
Requires-Dist: numpy>=1.16.5
